pyrigami/__init__.py
pyrigami/engraver/__init__.py
pyrigami/engraver/score.py
pyrigami/units/__init__.py
pyrigami/units/paper.py
pyrigami-0.1.0.dist-info/LICENSE
pyrigami-0.1.0.dist-info/WHEEL
pyrigami-0.1.0.dist-info/METADATA
pyrigami-0.1.0.dist-info/RECORD
