Metadata-Version: 2.1
Name: pyrigami
Version: 0.1.0
Summary: A library to draw declaratively on PDF/SVG/PNG.
Home-page: https://gitlab.com/ananthp/pyrigami
License: MIT
Author: Ananth P
Author-email: ananth.pattabiraman@gmail.com
Requires-Python: >=3.10,<4.0
Classifier: Development Status :: 4 - Beta
Classifier: Intended Audience :: Developers
Classifier: License :: OSI Approved :: MIT License
Classifier: Programming Language :: Python :: 3
Classifier: Programming Language :: Python :: 3.10
Classifier: Topic :: Multimedia :: Graphics
Classifier: Topic :: Multimedia :: Graphics :: Editors
Classifier: Topic :: Multimedia :: Graphics :: Editors :: Vector-Based
Requires-Dist: pydantic (>=1.9,<2.0)
Requires-Dist: qahirah (>=1.1,<2.0)
Project-URL: Repository, https://gitlab.com/ananthp/pyrigami
